qanon_mcp/__init__.py
qanon_mcp/posts.json
qanon_mcp-0.3.0.dist-info/METADATA
qanon_mcp-0.3.0.dist-info/WHEEL
qanon_mcp-0.3.0.dist-info/entry_points.txt
qanon_mcp-0.3.0.dist-info/licenses/LICENSE.md
qanon_mcp-0.3.0.dist-info/RECORD
